FDEint/FixedStepFDEint.py
FDEint/__init__.py
tests/__init__.py
tests/mittag_leffler.py
tests/test_FixedStepFDEint.py
FDEint-0.1.1.dist-info/LICENSE.txt
FDEint-0.1.1.dist-info/METADATA
FDEint-0.1.1.dist-info/WHEEL
FDEint-0.1.1.dist-info/top_level.txt
FDEint-0.1.1.dist-info/RECORD
