Metadata-Version: 2.1
Name: FDEint
Version: 0.1.1
Summary: A PyTorch-based solver for Neural Fractional Differential Equations (NFDE) using a predictor-corrector method.
Home-page: https://github.com/zimmer-ing/FDEint
Author: Bernd Zimmering
Author-email: bernd@zimmer-ing.de
License: MIT
Classifier: Programming Language :: Python :: 3
Classifier: License :: OSI Approved :: MIT License
Classifier: Operating System :: OS Independent
Requires-Python: >=3.8
License-File: LICENSE.txt
Requires-Dist: torch>=2.2.1
Requires-Dist: tqdm
Requires-Dist: numpy
